[
  {
    "id": 1,
    "first_name": "Celene",
    "last_name": "Picopp",
    "email": "cpicopp0@domainmarket.com",
    "gender": "Genderqueer",
    "job_tittle": "Professor"
  },
  {
    "id": 2,
    "first_name": "Marni",
    "last_name": "Mechan",
    "email": "mmechan1@zimbio.com",
    "gender": "Bigender",
    "job_tittle": "VP Sales"
  },
  {
    "id": 3,
    "first_name": "Alejandro",
    "last_name": "Germann",
    "email": "agermann2@vk.com",
    "gender": "Male",
    "job_tittle": "VP Sales"
  },
  {
    "id": 4,
    "first_name": "Aurel",
    "last_name": "Buxsey",
    "email": "abuxsey3@bbb.org",
    "gender": "Female",
    "job_tittle": "Accounting Assistant II"
  },
  {
    "id": 5,
    "first_name": "Heddi",
    "last_name": "Dudson",
    "email": "hdudson4@4shared.com",
    "gender": "Female",
    "job_tittle": "Senior Developer"
  },
  {
    "id": 6,
    "first_name": "Gerald",
    "last_name": "Cullip",
    "email": "gcullip5@ed.gov",
    "gender": "Male",
    "job_tittle": "Assistant Manager"
  },
  {
    "id": 7,
    "first_name": "Adelice",
    "last_name": "Barlie",
    "email": "abarlie6@dedecms.com",
    "gender": "Non-binary",
    "job_tittle": "Staff Scientist"
  },
  {
    "id": 8,
    "first_name": "Brittan",
    "last_name": "Moohan",
    "email": "bmoohan7@nih.gov",
    "gender": "Female",
    "job_tittle": "Financial Analyst"
  },
  {
    "id": 9,
    "first_name": "Marcel",
    "last_name": "Filipyev",
    "email": "mfilipyev8@bluehost.com",
    "gender": "Male",
    "job_tittle": "Safety Technician II"
  },
  {
    "id": 10,
    "first_name": "Sayre",
    "last_name": "Spurett",
    "email": "sspurett9@toplist.cz",
    "gender": "Female",
    "job_tittle": "Office Assistant II"
  },
  {
    "id": 11,
    "first_name": "Sadella",
    "last_name": "Aggio",
    "email": "saggioa@ocn.ne.jp",
    "gender": "Female",
    "job_tittle": "Professor"
  },
  {
    "id": 12,
    "first_name": "Care",
    "last_name": "Scargill",
    "email": "cscargillb@princeton.edu",
    "gender": "Male",
    "job_tittle": "Information Systems Manager"
  },
  {
    "id": 13,
    "first_name": "Marv",
    "last_name": "Swiggs",
    "email": "mswiggsc@51.la",
    "gender": "Male",
    "job_tittle": "Web Designer II"
  },
  {
    "id": 14,
    "first_name": "Corbett",
    "last_name": "Dodell",
    "email": "cdodelld@techcrunch.com",
    "gender": "Genderfluid",
    "job_tittle": "General Manager"
  },
  {
    "id": 15,
    "first_name": "Burt",
    "last_name": "Callender",
    "email": "bcallendere@guardian.co.uk",
    "gender": "Male",
    "job_tittle": "Assistant Professor"
  },
  {
    "id": 16,
    "first_name": "Flo",
    "last_name": "Phythien",
    "email": "fphythienf@ftc.gov",
    "gender": "Female",
    "job_tittle": "Account Coordinator"
  },
  {
    "id": 17,
    "first_name": "Bryant",
    "last_name": "Rowes",
    "email": "browesg@printfriendly.com",
    "gender": "Male",
    "job_tittle": "Executive Secretary"
  },
  {
    "id": 18,
    "first_name": "Jerry",
    "last_name": "McMeeking",
    "email": "jmcmeekingh@wordpress.org",
    "gender": "Male",
    "job_tittle": "VP Marketing"
  },
  {
    "id": 19,
    "first_name": "Bink",
    "last_name": "Browse",
    "email": "bbrowsei@bloglines.com",
    "gender": "Non-binary",
    "job_tittle": "Software Consultant"
  },
  {
    "id": 20,
    "first_name": "Averill",
    "last_name": "Ruslen",
    "email": "aruslenj@examiner.com",
    "gender": "Male",
    "job_tittle": "VP Accounting"
  },
  {
    "first_name": "shubhajit",
    "last_name": "biswal",
    "email": "shubhajit.dev@gmail.com",
    "job_tittle": "dev",
    "id": 21
  },
  {
    "first_name": "biswajit",
    "last_name": "biswal",
    "email": "biswajit.dev@gmail.com",
    "job_tittle": "dev",
    "id": 22
  }
]
